monofy/__init__.py
monofy/_version.py
monofy/tests.py
monofy/scripts/__init__.py
monofy/scripts/monofy.py
monofy-1.1.1.dist-info/LICENSE
monofy-1.1.1.dist-info/METADATA
monofy-1.1.1.dist-info/WHEEL
monofy-1.1.1.dist-info/entry_points.txt
monofy-1.1.1.dist-info/top_level.txt
monofy-1.1.1.dist-info/RECORD
