Metadata-Version: 2.1
Name: monofy
Version: 1.1.1
Summary: Multiple Processes in a Single Container
Author-email: "Bugsink B.V." <info@bugsink.com>
License: Copyright 2024 Bugsink B.V.
Project-URL: homepage, https://www.bugsink.com/blog/multi-process-docker-images/
Project-URL: repository, https://github.com/bugsink/monofy
Project-URL: issues, https://github.com/bugsink/monofy/issues
Classifier: Programming Language :: Python :: 3
Requires-Python: >=3.8
License-File: LICENSE
